mdwriter/__init__.py
mdwriter/mdwriter.py
mdwriter-0.1.1.dist-info/METADATA
mdwriter-0.1.1.dist-info/WHEEL
mdwriter-0.1.1.dist-info/top_level.txt
mdwriter-0.1.1.dist-info/zip-safe
mdwriter-0.1.1.dist-info/RECORD
